m2m_token/__init__.py
m2m_token/errors.py
m2m_token/token.py
tests/__init__.py
tests/tests_token.py
m2m_token-0.0.2.dist-info/LICENSE
m2m_token-0.0.2.dist-info/METADATA
m2m_token-0.0.2.dist-info/WHEEL
m2m_token-0.0.2.dist-info/top_level.txt
m2m_token-0.0.2.dist-info/RECORD
