Metadata-Version: 2.1
Name: m2m-token
Version: 0.0.2
Summary: Generates token for machine-to-machine authentication
Home-page: https://github.com/Maskime/m2m_token
Author: Maxime Faye
Author-email: maxime.faye@gmail.com
License: UNKNOWN
Platform: UNKNOWN
Classifier: Programming Language :: Python :: 3
Classifier: License :: OSI Approved :: MIT License
Classifier: Operating System :: OS Independent
Requires-Python: >=3.6
